phylline/__init__.py
phylline/pipelines.py
phylline/pipes.py
phylline/processors.py
phylline/links/__init__.py
phylline/links/clocked.py
phylline/links/events.py
phylline/links/links.py
phylline/links/loopback.py
phylline/links/streams.py
phylline/util/__init__.py
phylline/util/interfaces.py
phylline/util/iterables.py
phylline/util/logging.py
phylline/util/timing.py
tests/__init__.py
tests/unit/__init__.py
tests/unit/pipelines.py
tests/unit/pipes.py
tests/unit/processors.py
tests/unit/links/__init__.py
tests/unit/links/clocked.py
tests/unit/links/events.py
tests/unit/links/links.py
tests/unit/links/loopback.py
tests/unit/links/streams.py
tests/unit/util/__init__.py
tests/unit/util/interfaces.py
tests/unit/util/iterables.py
tests/unit/util/logging.py
tests/unit/util/timing.py
phylline-0.1.6.dist-info/LICENSE
phylline-0.1.6.dist-info/METADATA
phylline-0.1.6.dist-info/WHEEL
phylline-0.1.6.dist-info/top_level.txt
phylline-0.1.6.dist-info/RECORD
