Metadata-Version: 2.1
Name: phylline
Version: 0.1.6
Summary: Sans-I/O bidirectional data pipeline framework for making layered protocols.
Home-page: https://github.com/ethanjli/phylline
Author: Ethan Li
Author-email: lietk12@gmail.com
License: UNKNOWN
Platform: UNKNOWN
Requires-Dist: ohneio
